{"GlobalPropertiesHash":"ts1gCtwcpC58TpkRXM1bxsi/RNHkq41k4k8TTVT9LDA=","FingerprintPatternsHash":"gq3WsqcKBUGTSNle7RKKyXRIwh7M8ccEqOqYvIzoM04=","PropertyOverridesHash":"8ZRc1sGeVrPBx4lD717BgRaQekyh78QKV9SKsdt638U=","InputHashes":["0mRoE1bOYHo6UlgLGPEADZKWmzcKl0qoO5AyNwb\u002Bnu0=","ko8SWx8w4JSYADzJfA7mmk0hbitXcz5O82r/AeinxOs=","ZUMf8oTJY\u002B/GzQoYNv\u002Brm1P\u002B18g/b\u002BeKUHLxUuKSryQ=","FnZkJhqzpcHqzR3k/HnLHrJafMmlqYV9R6LpvQoFDK4=","SnB8CsrB\u002BF2CIg5T4bkHKKrf8QxGOkj5YmjcNbrb31s=","\u002BFZ4FaUzjvyBm/Zo8Z2Dstzrgn8I9JQNw2zvvL6TB8c=","NsIQt6FKPovnkFBj\u002B8hrAjFOqXo4qg/msBN5jl833mw=","VryZvhus973m20qnisEpesNomyfGB1MN4JsZno7QF5g=","QXjZ6gFenWqc0uikt8xtq1G/VXpbJz6bSUG\u002BvHicU/o=","HnWfmid87W7HYFfjcjhJgGQDZhsVgDBjd37VUxbjQDs=","v64xZI9IX5uINdUEyc\u002BMX36aKcTEkqWK\u002BaF/4E06y\u002BM=","OSX2zp53\u002BAK9kOo10H1ASjSlEPAsCJwCxCH/s8f17aw=","i9NGh7qociCxBRBAty7rWgG7dSCQQSySk2JjGBhwxf8=","u9CU8dNO47QzIHUOyfG10U8YrlZ1LahZa5fUD\u002BaH/B0=","UACsnprciJiaJP28sEQO6Nt3ta\u002BnVKnHLKo2\u002BuvYNn0=","tzxd3H0GhqGLkNhATjkYw/Y3Q0TSxt14YnIBsrRLxIg=","SXa5JUQz94TnvrPZh7ksFXwNGW\u002BDWlZ2htPK\u002BKt3afk=","zWcbsdHB5d3eWPTbU1Vj9x\u002BlkHMXZ1/czIihEOip9Dg=","ci74RBL/grfAVv1Z2Z2INVts0cQteUBez5YMQnlwFEI=","uhmyLKZYiMFmGAJFjjpEzOKpkNxXcd4fXRSZQV\u002Bs22M=","NBx/362VAbPetfGQuA2GFcTbW4Jih8PTa/r3QUZ3WWo=","9v9YHRTLEMYxY8nkO18M4yXv3q0Tw9mb8CmfFhd5NaY=","hH4C5U0CeaBdrmrdWodvcjkaKl/GtIC2oH4/UTkq\u002BE0=","9eINpyzHja1wkEEyqxw1U0lDtS1UL6rgaI62Z92jRXw=","euEjiOLzyr5CT3rDzrlbmB1owGre7vSFrPfz2Nek7No=","K26uOSDc0moxzYXPz6JmnxHSdDiK0l1W\u002BVAg5VWMpKc=","EDFcOHokjPRbfaLlE4RpgqxDfoIsFtO4ElVyzROghfg="],"CachedAssets":{"0mRoE1bOYHo6UlgLGPEADZKWmzcKl0qoO5AyNwb\u002Bnu0=":{"Identity":"C:\\Users\\franc\\Documents\\GitHub\\puntoNET\\pruevaDB1\\wwwroot\\app.css","SourceId":"pruevaDB1","SourceType":"Discovered","ContentRoot":"C:\\Users\\franc\\Documents\\GitHub\\puntoNET\\pruevaDB1\\wwwroot\\","BasePath":"_content/pruevaDB1","RelativePath":"app#[.{fingerprint}]?.css","AssetKind":"All","AssetMode":"All","AssetRole":"Primary","AssetMergeBehavior":null,"AssetMergeSource":"","RelatedAsset":null,"AssetTraitName":null,"AssetTraitValue":null,"Fingerprint":"da95v2qkru","Integrity":"u9qEka1auR7E3rd3/8/j8hkQdSOYj9bRJ4nYiFDR1sE=","CopyToOutputDirectory":"Never","CopyToPublishDirectory":"PreserveNewest","OriginalItemSpec":"wwwroot\\app.css","FileLength":2591,"LastWriteTime":"2025-10-27T21:04:34.8571285+00:00"},"ko8SWx8w4JSYADzJfA7mmk0hbitXcz5O82r/AeinxOs=":{"Identity":"C:\\Users\\franc\\Documents\\GitHub\\puntoNET\\pruevaDB1\\wwwroot\\bootstrap\\bootstrap.min.css","SourceId":"pruevaDB1","SourceType":"Discovered","ContentRoot":"C:\\Users\\franc\\Documents\\GitHub\\puntoNET\\pruevaDB1\\wwwroot\\","BasePath":"_content/pruevaDB1","RelativePath":"bootstrap/bootstrap.min#[.{fingerprint}]?.css","AssetKind":"All","AssetMode":"All","AssetRole":"Primary","AssetMergeBehavior":null,"AssetMergeSource":"","RelatedAsset":null,"AssetTraitName":null,"AssetTraitValue":null,"Fingerprint":"6gzpyzhau4","Integrity":"SiIVMGgRhdXjKSTIddX7mh9IbOXVcwQWc7/p4nS6D/0=","CopyToOutputDirectory":"Never","CopyToPublishDirectory":"PreserveNewest","OriginalItemSpec":"wwwroot\\bootstrap\\bootstrap.min.css","FileLength":162726,"LastWriteTime":"2025-10-27T21:04:35.0403333+00:00"},"ZUMf8oTJY\u002B/GzQoYNv\u002Brm1P\u002B18g/b\u002BeKUHLxUuKSryQ=":{"Identity":"C:\\Users\\franc\\Documents\\GitHub\\puntoNET\\pruevaDB1\\wwwroot\\bootstrap\\bootstrap.min.css.map","SourceId":"pruevaDB1","SourceType":"Discovered","ContentRoot":"C:\\Users\\franc\\Documents\\GitHub\\puntoNET\\pruevaDB1\\wwwroot\\","BasePath":"_content/pruevaDB1","RelativePath":"bootstrap/bootstrap.min.css#[.{fingerprint}]?.map","AssetKind":"All","AssetMode":"All","AssetRole":"Primary","AssetMergeBehavior":null,"AssetMergeSource":"","RelatedAsset":null,"AssetTraitName":null,"AssetTraitValue":null,"Fingerprint":"8inm30yfxf","Integrity":"gBwg2tmA0Ci2u54gMF1jNCVku6vznarkLS6D76htNNQ=","CopyToOutputDirectory":"Never","CopyToPublishDirectory":"PreserveNewest","OriginalItemSpec":"wwwroot\\bootstrap\\bootstrap.min.css.map","FileLength":449111,"LastWriteTime":"2025-10-27T21:04:35.278041+00:00"},"FnZkJhqzpcHqzR3k/HnLHrJafMmlqYV9R6LpvQoFDK4=":{"Identity":"C:\\Users\\franc\\Documents\\GitHub\\puntoNET\\pruevaDB1\\wwwroot\\favicon.png","SourceId":"pruevaDB1","SourceType":"Discovered","ContentRoot":"C:\\Users\\franc\\Documents\\GitHub\\puntoNET\\pruevaDB1\\wwwroot\\","BasePath":"_content/pruevaDB1","RelativePath":"favicon#[.{fingerprint}]?.png","AssetKind":"All","AssetMode":"All","AssetRole":"Primary","AssetMergeBehavior":null,"AssetMergeSource":"","RelatedAsset":null,"AssetTraitName":null,"AssetTraitValue":null,"Fingerprint":"ifv42okdf2","Integrity":"4mWsDy3aHl36ZbGt8zByK7Pvd4kRUoNgTYzRnwmPHwg=","CopyToOutputDirectory":"Never","CopyToPublishDirectory":"PreserveNewest","OriginalItemSpec":"wwwroot\\favicon.png","FileLength":1148,"LastWriteTime":"2025-10-27T21:04:35.533492+00:00"}},"CachedCopyCandidates":{}}